{"results":[{"created_at":"Fri Mar 01 14:29:13 +0000 2019","id":1101489571135660038,"id_str":"1101489571135660038","text":"Before Day 3 of the #NFLCombine begins, @JumboHart and @MeganOBsports recap Day 2 from Indianapolis. https:\/\/t.co\/GhiYTFclei","display_text_range":[0,100],"source":"\u003ca href=\"https:\/\/studio.twitter.com\" rel=\"nofollow\"\u003eTwitter Media Studio\u003c\/a\u003e","truncated":false,"in_reply_to_status_id":null,"in_reply_to_status_id_str":null,"in_reply_to_user_id":null,"in_reply_to_user_id_str":null,"in_reply_to_screen_name":null,"user":{"id":31126587,"id_str":"31126587","name":"New England Patriots","screen_name":"Patriots","location":null,"url":"http:\/\/patriots.com","description":"Official Twitter of the 6-time champion New England Patriots #GoPats","translator_type":"regular","protected":false,"verified":true,"followers_count":4565691,"friends_count":288,"listed_count":12822,"favourites_count":14810,"statuses_count":53728,"created_at":"Tue Apr 14 13:56:51 +0000 2009","utc_offset":null,"time_zone":null,"geo_enabled":true,"lang":null,"contributors_enabled":false,"is_translator":false,"profile_background_color":"041831","profile_background_image_url":"http:\/\/abs.twimg.com\/images\/themes\/theme1\/bg.png","profile_background_image_url_https":"https:\/\/abs.twimg.com\/images\/themes\/theme1\/bg.png","profile_background_tile":false,"profile_link_color":"133962","profile_sidebar_border_color":"FFFFFF","profile_sidebar_fill_color":"6581A4","profile_text_color":"041831","profile_use_background_image":true,"profile_image_url":"http:\/\/pbs.twimg.com\/profile_images\/1323983398818488322\/WtrQO4He_normal.jpg","profile_image_url_https":"https:\/\/pbs.twimg.com\/profile_images\/1323983398818488322\/WtrQO4He_normal.jpg","profile_banner_url":"https:\/\/pbs.twimg.com\/profile_banners\/31126587\/1601660342","default_profile":false,"default_profile_image":false,"following":null,"follow_request_sent":null,"notifications":null},"geo":null,"coordinates":null,"place":null,"contributors":null,"is_quote_status":false,"quote_count":0,"reply_count":4,"retweet_count":22,"favorite_count":212,"entities":{"hashtags":[{"text":"NFLCombine","indices":[20,31]}],"urls":[],"user_mentions":[{"screen_name":"JumboHart","name":"Andy Hart","id":39809336,"id_str":"39809336","indices":[40,50]},{"screen_name":"MeganOBsports","name":"Megan O'Brien","id":584036166,"id_str":"584036166","indices":[55,69]}],"symbols":[],"media":[{"id":1101486388455854080,"id_str":"1101486388455854080","indices":[101,124],"additional_media_info":{"title":"","description":"","embeddable":true,"monetizable":false},"media_url":"http:\/\/pbs.twimg.com\/media\/D0lGceBX0AEC5mo.jpg","media_url_https":"https:\/\/pbs.twimg.com\/media\/D0lGceBX0AEC5mo.jpg","url":"https:\/\/t.co\/GhiYTFclei","display_url":"pic.twitter.com\/GhiYTFclei","expanded_url":"https:\/\/twitter.com\/Patriots\/status\/1101489571135660038\/video\/1","type":"photo","sizes":{"thumb":{"w":150,"h":150,"resize":"crop"},"large":{"w":1920,"h":1080,"resize":"fit"},"medium":{"w":1200,"h":675,"resize":"fit"},"small":{"w":680,"h":383,"resize":"fit"}}}]},"extended_entities":{"media":[{"id":1101486388455854080,"id_str":"1101486388455854080","indices":[101,124],"additional_media_info":{"title":"","description":"","embeddable":true,"monetizable":false},"media_url":"http:\/\/pbs.twimg.com\/media\/D0lGceBX0AEC5mo.jpg","media_url_https":"https:\/\/pbs.twimg.com\/media\/D0lGceBX0AEC5mo.jpg","url":"https:\/\/t.co\/GhiYTFclei","display_url":"pic.twitter.com\/GhiYTFclei","expanded_url":"https:\/\/twitter.com\/Patriots\/status\/1101489571135660038\/video\/1","type":"video","video_info":{"aspect_ratio":[16,9],"duration_millis":169136,"variants":[{"bitrate":288000,"content_type":"video\/mp4","url":"https:\/\/video.twimg.com\/amplify_video\/1101486388455854080\/vid\/320x180\/9l2sNyLPxiTchIjv.mp4?tag=9"},{"bitrate":832000,"content_type":"video\/mp4","url":"https:\/\/video.twimg.com\/amplify_video\/1101486388455854080\/vid\/640x360\/jUNCHeGqTEmXyRQk.mp4?tag=9"},{"content_type":"application\/x-mpegURL","url":"https:\/\/video.twimg.com\/amplify_video\/1101486388455854080\/pl\/FFCJwSMV8uL0Mz_M.m3u8?tag=9"},{"bitrate":2176000,"content_type":"video\/mp4","url":"https:\/\/video.twimg.com\/amplify_video\/1101486388455854080\/vid\/1280x720\/Vp-Cz4QoYQVGRAxy.mp4?tag=9"}]},"sizes":{"thumb":{"w":150,"h":150,"resize":"crop"},"large":{"w":1920,"h":1080,"resize":"fit"},"medium":{"w":1200,"h":675,"resize":"fit"},"small":{"w":680,"h":383,"resize":"fit"}}}]},"favorited":false,"retweeted":false,"possibly_sensitive":false,"filter_level":"low","lang":"en","matching_rules":[{"tag":null}]},{"created_at":"Fri Mar 01 13:12:03 +0000 2019","id":1101470153257168897,"id_str":"1101470153257168897","text":"Happy birthday, Keionta! https:\/\/t.co\/3OzJwxVh0m","display_text_range":[0,24],"source":"\u003ca href=\"https:\/\/buffer.com\" rel=\"nofollow\"\u003eBuffer\u003c\/a\u003e","truncated":false,"in_reply_to_status_id":null,"in_reply_to_status_id_str":null,"in_reply_to_user_id":null,"in_reply_to_user_id_str":null,"in_reply_to_screen_name":null,"user":{"id":31126587,"id_str":"31126587","name":"New England Patriots","screen_name":"Patriots","location":null,"url":"http:\/\/patriots.com","description":"Official Twitter of the 6-time champion New England Patriots #GoPats","translator_type":"regular","protected":false,"verified":true,"followers_count":4565691,"friends_count":288,"listed_count":12822,"favourites_count":14810,"statuses_count":53728,"created_at":"Tue Apr 14 13:56:51 +0000 2009","utc_offset":null,"time_zone":null,"geo_enabled":true,"lang":null,"contributors_enabled":false,"is_translator":false,"profile_background_color":"041831","profile_background_image_url":"http:\/\/abs.twimg.com\/images\/themes\/theme1\/bg.png","profile_background_image_url_https":"https:\/\/abs.twimg.com\/images\/themes\/theme1\/bg.png","profile_background_tile":false,"profile_link_color":"133962","profile_sidebar_border_color":"FFFFFF","profile_sidebar_fill_color":"6581A4","profile_text_color":"041831","profile_use_background_image":true,"profile_image_url":"http:\/\/pbs.twimg.com\/profile_images\/1323983398818488322\/WtrQO4He_normal.jpg","profile_image_url_https":"https:\/\/pbs.twimg.com\/profile_images\/1323983398818488322\/WtrQO4He_normal.jpg","profile_banner_url":"https:\/\/pbs.twimg.com\/profile_banners\/31126587\/1601660342","default_profile":false,"default_profile_image":false,"following":null,"follow_request_sent":null,"notifications":null},"geo":null,"coordinates":null,"place":null,"contributors":null,"is_quote_status":false,"quote_count":5,"reply_count":30,"retweet_count":114,"favorite_count":1490,"entities":{"hashtags":[],"urls":[],"user_mentions":[],"symbols":[],"media":[{"id":1101470151436877829,"id_str":"1101470151436877829","indices":[25,48],"media_url":"http:\/\/pbs.twimg.com\/media\/D0k1RFMXQAUWx5a.jpg","media_url_https":"https:\/\/pbs.twimg.com\/media\/D0k1RFMXQAUWx5a.jpg","url":"https:\/\/t.co\/3OzJwxVh0m","display_url":"pic.twitter.com\/3OzJwxVh0m","expanded_url":"https:\/\/twitter.com\/Patriots\/status\/1101470153257168897\/photo\/1","type":"photo","sizes":{"large":{"w":912,"h":512,"resize":"fit"},"thumb":{"w":150,"h":150,"resize":"crop"},"medium":{"w":912,"h":512,"resize":"fit"},"small":{"w":680,"h":382,"resize":"fit"}}}]},"extended_entities":{"media":[{"id":1101470151436877829,"id_str":"1101470151436877829","indices":[25,48],"media_url":"http:\/\/pbs.twimg.com\/media\/D0k1RFMXQAUWx5a.jpg","media_url_https":"https:\/\/pbs.twimg.com\/media\/D0k1RFMXQAUWx5a.jpg","url":"https:\/\/t.co\/3OzJwxVh0m","display_url":"pic.twitter.com\/3OzJwxVh0m","expanded_url":"https:\/\/twitter.com\/Patriots\/status\/1101470153257168897\/photo\/1","type":"photo","sizes":{"large":{"w":912,"h":512,"resize":"fit"},"thumb":{"w":150,"h":150,"resize":"crop"},"medium":{"w":912,"h":512,"resize":"fit"},"small":{"w":680,"h":382,"resize":"fit"}}}]},"favorited":false,"retweeted":false,"possibly_sensitive":false,"filter_level":"low","lang":"en","matching_rules":[{"tag":null}]},{"created_at":"Fri Mar 01 13:08:01 +0000 2019","id":1101469138143318016,"id_str":"1101469138143318016","text":"Supporting in the \u2744\n\nBest #PatriotsPETriot submissions from the month of February: https:\/\/t.co\/enOtj8TGHU https:\/\/t.co\/6ywi5PHuDh","display_text_range":[0,106],"source":"\u003ca href=\"https:\/\/buffer.com\" rel=\"nofollow\"\u003eBuffer\u003c\/a\u003e","truncated":false,"in_reply_to_status_id":null,"in_reply_to_status_id_str":null,"in_reply_to_user_id":null,"in_reply_to_user_id_str":null,"in_reply_to_screen_name":null,"user":{"id":31126587,"id_str":"31126587","name":"New England Patriots","screen_name":"Patriots","location":null,"url":"http:\/\/patriots.com","description":"Official Twitter of the 6-time champion New England Patriots #GoPats","translator_type":"regular","protected":false,"verified":true,"followers_count":4565691,"friends_count":288,"listed_count":12822,"favourites_count":14810,"statuses_count":53728,"created_at":"Tue Apr 14 13:56:51 +0000 2009","utc_offset":null,"time_zone":null,"geo_enabled":true,"lang":null,"contributors_enabled":false,"is_translator":false,"profile_background_color":"041831","profile_background_image_url":"http:\/\/abs.twimg.com\/images\/themes\/theme1\/bg.png","profile_background_image_url_https":"https:\/\/abs.twimg.com\/images\/themes\/theme1\/bg.png","profile_background_tile":false,"profile_link_color":"133962","profile_sidebar_border_color":"FFFFFF","profile_sidebar_fill_color":"6581A4","profile_text_color":"041831","profile_use_background_image":true,"profile_image_url":"http:\/\/pbs.twimg.com\/profile_images\/1323983398818488322\/WtrQO4He_normal.jpg","profile_image_url_https":"https:\/\/pbs.twimg.com\/profile_images\/1323983398818488322\/WtrQO4He_normal.jpg","profile_banner_url":"https:\/\/pbs.twimg.com\/profile_banners\/31126587\/1601660342","default_profile":false,"default_profile_image":false,"following":null,"follow_request_sent":null,"notifications":null},"geo":null,"coordinates":null,"place":null,"contributors":null,"is_quote_status":false,"quote_count":1,"reply_count":2,"retweet_count":36,"favorite_count":312,"entities":{"hashtags":[{"text":"PatriotsPETriot","indices":[26,42]}],"urls":[{"url":"https:\/\/t.co\/enOtj8TGHU","expanded_url":"http:\/\/bit.ly\/2BTTWms","display_url":"bit.ly\/2BTTWms","indices":[83,106]}],"user_mentions":[],"symbols":[],"media":[{"id":1101469136381767680,"id_str":"1101469136381767680","indices":[107,130],"media_url":"http:\/\/pbs.twimg.com\/media\/D0k0V_0XcAAFzcZ.jpg","media_url_https":"https:\/\/pbs.twimg.com\/media\/D0k0V_0XcAAFzcZ.jpg","url":"https:\/\/t.co\/6ywi5PHuDh","display_url":"pic.twitter.com\/6ywi5PHuDh","expanded_url":"https:\/\/twitter.com\/Patriots\/status\/1101469138143318016\/photo\/1","type":"photo","sizes":{"medium":{"w":912,"h":512,"resize":"fit"},"thumb":{"w":150,"h":150,"resize":"crop"},"large":{"w":912,"h":512,"resize":"fit"},"small":{"w":680,"h":382,"resize":"fit"}}}]},"extended_entities":{"media":[{"id":1101469136381767680,"id_str":"1101469136381767680","indices":[107,130],"media_url":"http:\/\/pbs.twimg.com\/media\/D0k0V_0XcAAFzcZ.jpg","media_url_https":"https:\/\/pbs.twimg.com\/media\/D0k0V_0XcAAFzcZ.jpg","url":"https:\/\/t.co\/6ywi5PHuDh","display_url":"pic.twitter.com\/6ywi5PHuDh","expanded_url":"https:\/\/twitter.com\/Patriots\/status\/1101469138143318016\/photo\/1","type":"photo","sizes":{"medium":{"w":912,"h":512,"resize":"fit"},"thumb":{"w":150,"h":150,"resize":"crop"},"large":{"w":912,"h":512,"resize":"fit"},"small":{"w":680,"h":382,"resize":"fit"}}}]},"favorited":false,"retweeted":false,"possibly_sensitive":false,"filter_level":"low","lang":"en","matching_rules":[{"tag":null}]},{"created_at":"Fri Mar 01 02:15:02 +0000 2019","id":1101304809943171072,"id_str":"1101304809943171072","text":"Murray measures up, RBs &amp; offensive linemen meet the media &amp; McVay, Gruden talk #Patriots.\n\n@DonBanks's Snap Judgme\u2026 https:\/\/t.co\/IdI1gNK5xn","display_text_range":[0,140],"source":"\u003ca href=\"https:\/\/buffer.com\" rel=\"nofollow\"\u003eBuffer\u003c\/a\u003e","truncated":true,"in_reply_to_status_id":null,"in_reply_to_status_id_str":null,"in_reply_to_user_id":null,"in_reply_to_user_id_str":null,"in_reply_to_screen_name":null,"user":{"id":31126587,"id_str":"31126587","name":"New England Patriots","screen_name":"Patriots","location":null,"url":"http:\/\/patriots.com","description":"Official Twitter of the 6-time champion New England Patriots #GoPats","translator_type":"regular","protected":false,"verified":true,"followers_count":4565691,"friends_count":288,"listed_count":12822,"favourites_count":14810,"statuses_count":53728,"created_at":"Tue Apr 14 13:56:51 +0000 2009","utc_offset":null,"time_zone":null,"geo_enabled":true,"lang":null,"contributors_enabled":false,"is_translator":false,"profile_background_color":"041831","profile_background_image_url":"http:\/\/abs.twimg.com\/images\/themes\/theme1\/bg.png","profile_background_image_url_https":"https:\/\/abs.twimg.com\/images\/themes\/theme1\/bg.png","profile_background_tile":false,"profile_link_color":"133962","profile_sidebar_border_color":"FFFFFF","profile_sidebar_fill_color":"6581A4","profile_text_color":"041831","profile_use_background_image":true,"profile_image_url":"http:\/\/pbs.twimg.com\/profile_images\/1323983398818488322\/WtrQO4He_normal.jpg","profile_image_url_https":"https:\/\/pbs.twimg.com\/profile_images\/1323983398818488322\/WtrQO4He_normal.jpg","profile_banner_url":"https:\/\/pbs.twimg.com\/profile_banners\/31126587\/1601660342","default_profile":false,"default_profile_image":false,"following":null,"follow_request_sent":null,"notifications":null},"geo":null,"coordinates":null,"place":null,"contributors":null,"is_quote_status":false,"extended_tweet":{"full_text":"Murray measures up, RBs &amp; offensive linemen meet the media &amp; McVay, Gruden talk #Patriots.\n\n@DonBanks's Snap Judgments from Day 2 of the #NFLCombine:  https:\/\/t.co\/sAUcBcndax https:\/\/t.co\/pVXQ6EXVWE","display_text_range":[0,182],"entities":{"hashtags":[{"text":"Patriots","indices":[88,97]},{"text":"NFLCombine","indices":[145,156]}],"urls":[{"url":"https:\/\/t.co\/sAUcBcndax","expanded_url":"http:\/\/bit.ly\/2EE9vQY","display_url":"bit.ly\/2EE9vQY","indices":[159,182]}],"user_mentions":[{"screen_name":"DonBanks","name":"Don Banks","id":34722669,"id_str":"34722669","indices":[100,109]}],"symbols":[],"media":[{"id":1101304808475119616,"id_str":"1101304808475119616","indices":[183,206],"media_url":"http:\/\/pbs.twimg.com\/media\/D0ie42qW0AATJ4j.jpg","media_url_https":"https:\/\/pbs.twimg.com\/media\/D0ie42qW0AATJ4j.jpg","url":"https:\/\/t.co\/pVXQ6EXVWE","display_url":"pic.twitter.com\/pVXQ6EXVWE","expanded_url":"https:\/\/twitter.com\/Patriots\/status\/1101304809943171072\/photo\/1","type":"photo","sizes":{"medium":{"w":1200,"h":675,"resize":"fit"},"thumb":{"w":150,"h":150,"resize":"crop"},"large":{"w":1280,"h":720,"resize":"fit"},"small":{"w":680,"h":383,"resize":"fit"}}}]},"extended_entities":{"media":[{"id":1101304808475119616,"id_str":"1101304808475119616","indices":[183,206],"media_url":"http:\/\/pbs.twimg.com\/media\/D0ie42qW0AATJ4j.jpg","media_url_https":"https:\/\/pbs.twimg.com\/media\/D0ie42qW0AATJ4j.jpg","url":"https:\/\/t.co\/pVXQ6EXVWE","display_url":"pic.twitter.com\/pVXQ6EXVWE","expanded_url":"https:\/\/twitter.com\/Patriots\/status\/1101304809943171072\/photo\/1","type":"photo","sizes":{"medium":{"w":1200,"h":675,"resize":"fit"},"thumb":{"w":150,"h":150,"resize":"crop"},"large":{"w":1280,"h":720,"resize":"fit"},"small":{"w":680,"h":383,"resize":"fit"}}}]}},"quote_count":1,"reply_count":3,"retweet_count":21,"favorite_count":207,"entities":{"hashtags":[{"text":"Patriots","indices":[88,97]}],"urls":[{"url":"https:\/\/t.co\/IdI1gNK5xn","expanded_url":"https:\/\/twitter.com\/i\/web\/status\/1101304809943171072","display_url":"twitter.com\/i\/web\/status\/1\u2026","indices":[125,148]}],"user_mentions":[{"screen_name":"DonBanks","name":"Don Banks","id":34722669,"id_str":"34722669","indices":[100,109]}],"symbols":[]},"favorited":false,"retweeted":false,"possibly_sensitive":false,"filter_level":"low","lang":"en","matching_rules":[{"tag":null}]},{"created_at":"Fri Mar 01 01:16:00 +0000 2019","id":1101289952334077953,"id_str":"1101289952334077953","text":"Plenty of #Patriots praise from NFL coaches on Day 2 of the Combine.\n\nMcVay talks the defense, Gruden on the offens\u2026 https:\/\/t.co\/j5bI659s2v","display_text_range":[0,140],"source":"\u003ca href=\"https:\/\/studio.twitter.com\" rel=\"nofollow\"\u003eTwitter Media Studio\u003c\/a\u003e","truncated":true,"in_reply_to_status_id":null,"in_reply_to_status_id_str":null,"in_reply_to_user_id":null,"in_reply_to_user_id_str":null,"in_reply_to_screen_name":null,"user":{"id":31126587,"id_str":"31126587","name":"New England Patriots","screen_name":"Patriots","location":null,"url":"http:\/\/patriots.com","description":"Official Twitter of the 6-time champion New England Patriots #GoPats","translator_type":"regular","protected":false,"verified":true,"followers_count":4565691,"friends_count":288,"listed_count":12822,"favourites_count":14810,"statuses_count":53728,"created_at":"Tue Apr 14 13:56:51 +0000 2009","utc_offset":null,"time_zone":null,"geo_enabled":true,"lang":null,"contributors_enabled":false,"is_translator":false,"profile_background_color":"041831","profile_background_image_url":"http:\/\/abs.twimg.com\/images\/themes\/theme1\/bg.png","profile_background_image_url_https":"https:\/\/abs.twimg.com\/images\/themes\/theme1\/bg.png","profile_background_tile":false,"profile_link_color":"133962","profile_sidebar_border_color":"FFFFFF","profile_sidebar_fill_color":"6581A4","profile_text_color":"041831","profile_use_background_image":true,"profile_image_url":"http:\/\/pbs.twimg.com\/profile_images\/1323983398818488322\/WtrQO4He_normal.jpg","profile_image_url_https":"https:\/\/pbs.twimg.com\/profile_images\/1323983398818488322\/WtrQO4He_normal.jpg","profile_banner_url":"https:\/\/pbs.twimg.com\/profile_banners\/31126587\/1601660342","default_profile":false,"default_profile_image":false,"following":null,"follow_request_sent":null,"notifications":null},"geo":null,"coordinates":null,"place":null,"contributors":null,"is_quote_status":false,"extended_tweet":{"full_text":"Plenty of #Patriots praise from NFL coaches on Day 2 of the Combine.\n\nMcVay talks the defense, Gruden on the offense. https:\/\/t.co\/0MOFfzwd1y","display_text_range":[0,117],"entities":{"hashtags":[{"text":"Patriots","indices":[10,19]}],"urls":[],"user_mentions":[],"symbols":[],"media":[{"id":1101256786542292992,"id_str":"1101256786542292992","indices":[118,141],"additional_media_info":{"title":"","description":"","embeddable":true,"monetizable":false},"media_url":"http:\/\/pbs.twimg.com\/media\/D0h02qYWsAA7aiH.jpg","media_url_https":"https:\/\/pbs.twimg.com\/media\/D0h02qYWsAA7aiH.jpg","url":"https:\/\/t.co\/0MOFfzwd1y","display_url":"pic.twitter.com\/0MOFfzwd1y","expanded_url":"https:\/\/twitter.com\/Patriots\/status\/1101289952334077953\/video\/1","type":"video","video_info":{"aspect_ratio":[16,9],"duration_millis":86753,"variants":[{"bitrate":2176000,"content_type":"video\/mp4","url":"https:\/\/video.twimg.com\/amplify_video\/1101256786542292992\/vid\/1280x720\/Gdtl6wh1JGE5zzgK.mp4?tag=9"},{"bitrate":832000,"content_type":"video\/mp4","url":"https:\/\/video.twimg.com\/amplify_video\/1101256786542292992\/vid\/640x360\/kqCr30Vp3hZWMqN9.mp4?tag=9"},{"bitrate":288000,"content_type":"video\/mp4","url":"https:\/\/video.twimg.com\/amplify_video\/1101256786542292992\/vid\/320x180\/vNOP7UWTavepsUwg.mp4?tag=9"},{"content_type":"application\/x-mpegURL","url":"https:\/\/video.twimg.com\/amplify_video\/1101256786542292992\/pl\/VGTD_ou2RTuig26w.m3u8?tag=9"}]},"sizes":{"thumb":{"w":150,"h":150,"resize":"crop"},"small":{"w":680,"h":378,"resize":"fit"},"large":{"w":694,"h":386,"resize":"fit"},"medium":{"w":694,"h":386,"resize":"fit"}}}]},"extended_entities":{"media":[{"id":1101256786542292992,"id_str":"1101256786542292992","indices":[118,141],"additional_media_info":{"title":"","description":"","embeddable":true,"monetizable":false},"media_url":"http:\/\/pbs.twimg.com\/media\/D0h02qYWsAA7aiH.jpg","media_url_https":"https:\/\/pbs.twimg.com\/media\/D0h02qYWsAA7aiH.jpg","url":"https:\/\/t.co\/0MOFfzwd1y","display_url":"pic.twitter.com\/0MOFfzwd1y","expanded_url":"https:\/\/twitter.com\/Patriots\/status\/1101289952334077953\/video\/1","type":"video","video_info":{"aspect_ratio":[16,9],"duration_millis":86753,"variants":[{"bitrate":2176000,"content_type":"video\/mp4","url":"https:\/\/video.twimg.com\/amplify_video\/1101256786542292992\/vid\/1280x720\/Gdtl6wh1JGE5zzgK.mp4?tag=9"},{"bitrate":832000,"content_type":"video\/mp4","url":"https:\/\/video.twimg.com\/amplify_video\/1101256786542292992\/vid\/640x360\/kqCr30Vp3hZWMqN9.mp4?tag=9"},{"bitrate":288000,"content_type":"video\/mp4","url":"https:\/\/video.twimg.com\/amplify_video\/1101256786542292992\/vid\/320x180\/vNOP7UWTavepsUwg.mp4?tag=9"},{"content_type":"application\/x-mpegURL","url":"https:\/\/video.twimg.com\/amplify_video\/1101256786542292992\/pl\/VGTD_ou2RTuig26w.m3u8?tag=9"}]},"sizes":{"thumb":{"w":150,"h":150,"resize":"crop"},"small":{"w":680,"h":378,"resize":"fit"},"large":{"w":694,"h":386,"resize":"fit"},"medium":{"w":694,"h":386,"resize":"fit"}}}]}},"quote_count":2,"reply_count":2,"retweet_count":61,"favorite_count":571,"entities":{"hashtags":[{"text":"Patriots","indices":[10,19]}],"urls":[{"url":"https:\/\/t.co\/j5bI659s2v","expanded_url":"https:\/\/twitter.com\/i\/web\/status\/1101289952334077953","display_url":"twitter.com\/i\/web\/status\/1\u2026","indices":[117,140]}],"user_mentions":[],"symbols":[]},"favorited":false,"retweeted":false,"possibly_sensitive":false,"filter_level":"low","lang":"en","matching_rules":[{"tag":null}]}],"requestParameters":{"maxResults":100,"fromDate":"201903010000","toDate":"201903312359"}}